ansys/api/speos/grpc_stub.py
ansys/api/speos/LTF/v1/LTF_pb2.py
ansys/api/speos/LTF/v1/LTF_pb2_grpc.py
ansys/api/speos/bsdf/v1/anisotropic_bsdf_pb2.py
ansys/api/speos/bsdf/v1/anisotropic_bsdf_pb2_grpc.py
ansys/api/speos/bsdf/v1/bsdf_creation_pb2.py
ansys/api/speos/bsdf/v1/bsdf_creation_pb2_grpc.py
ansys/api/speos/bsdf/v1/spectral_bsdf_pb2.py
ansys/api/speos/bsdf/v1/spectral_bsdf_pb2_grpc.py
ansys/api/speos/example/v1/example_pb2.py
ansys/api/speos/example/v1/example_pb2_grpc.py
ansys/api/speos/file/v1/file_transfer.py
ansys/api/speos/file/v1/file_transfer_pb2.py
ansys/api/speos/file/v1/file_transfer_pb2_grpc.py
ansys/api/speos/job/v1/job_pb2.py
ansys/api/speos/job/v1/job_pb2_grpc.py
ansys/api/speos/live_preview/v1/live_preview_pb2.py
ansys/api/speos/live_preview/v1/live_preview_pb2_grpc.py
ansys/api/speos/lpf/v1/lpf_file_reader_pb2.py
ansys/api/speos/lpf/v1/lpf_file_reader_pb2_grpc.py
ansys/api/speos/lpf/v2/lpf_file_reader_pb2.py
ansys/api/speos/lpf/v2/lpf_file_reader_pb2_grpc.py
ansys/api/speos/simulation/v1/simulation_pb2.py
ansys/api/speos/simulation/v1/simulation_pb2_grpc.py
ansys/api/speos/xmp/v1/xmp_file_pb2.py
ansys/api/speos/xmp/v1/xmp_file_pb2_grpc.py
ansys_optics_speos_grpcapi-8.0.0.dist-info/METADATA
ansys_optics_speos_grpcapi-8.0.0.dist-info/WHEEL
ansys_optics_speos_grpcapi-8.0.0.dist-info/top_level.txt
ansys_optics_speos_grpcapi-8.0.0.dist-info/RECORD
